odoo10_addon_l10n_it_corrispettivi_sale-10.0.1.0.3-nspkg.pth
odoo/addons/l10n_it_corrispettivi_sale/README.rst
odoo/addons/l10n_it_corrispettivi_sale/__init__.py
odoo/addons/l10n_it_corrispettivi_sale/__manifest__.py
odoo/addons/l10n_it_corrispettivi_sale/i18n/ca.po
odoo/addons/l10n_it_corrispettivi_sale/i18n/de.po
odoo/addons/l10n_it_corrispettivi_sale/i18n/el_GR.po
odoo/addons/l10n_it_corrispettivi_sale/i18n/es.po
odoo/addons/l10n_it_corrispettivi_sale/i18n/es_ES.po
odoo/addons/l10n_it_corrispettivi_sale/i18n/es_VE.po
odoo/addons/l10n_it_corrispettivi_sale/i18n/fi.po
odoo/addons/l10n_it_corrispettivi_sale/i18n/fr.po
odoo/addons/l10n_it_corrispettivi_sale/i18n/hr.po
odoo/addons/l10n_it_corrispettivi_sale/i18n/hr_HR.po
odoo/addons/l10n_it_corrispettivi_sale/i18n/hu.po
odoo/addons/l10n_it_corrispettivi_sale/i18n/it.po
odoo/addons/l10n_it_corrispettivi_sale/i18n/l10n_it_corrispettivi_sale.pot
odoo/addons/l10n_it_corrispettivi_sale/i18n/nl.po
odoo/addons/l10n_it_corrispettivi_sale/i18n/pt.po
odoo/addons/l10n_it_corrispettivi_sale/i18n/pt_BR.po
odoo/addons/l10n_it_corrispettivi_sale/i18n/ro.po
odoo/addons/l10n_it_corrispettivi_sale/i18n/sl.po
odoo/addons/l10n_it_corrispettivi_sale/i18n/tr.po
odoo/addons/l10n_it_corrispettivi_sale/i18n/vi_VN.po
odoo/addons/l10n_it_corrispettivi_sale/i18n/zh_CN.po
odoo/addons/l10n_it_corrispettivi_sale/models/__init__.py
odoo/addons/l10n_it_corrispettivi_sale/models/sale.py
odoo/addons/l10n_it_corrispettivi_sale/static/description/icon.png
odoo/addons/l10n_it_corrispettivi_sale/views/sale_view.xml
odoo10_addon_l10n_it_corrispettivi_sale-10.0.1.0.3.dist-info/METADATA
odoo10_addon_l10n_it_corrispettivi_sale-10.0.1.0.3.dist-info/WHEEL
odoo10_addon_l10n_it_corrispettivi_sale-10.0.1.0.3.dist-info/namespace_packages.txt
odoo10_addon_l10n_it_corrispettivi_sale-10.0.1.0.3.dist-info/top_level.txt
odoo10_addon_l10n_it_corrispettivi_sale-10.0.1.0.3.dist-info/RECORD
