Metadata-Version: 2.1
Name: odoo10-addon-l10n-it-corrispettivi-sale
Version: 10.0.1.0.3
Summary: Modulo per integrare i corrispettivi in odoo con gli ordini di vendita.
Home-page: https://github.com/OCA/l10n-italy/tree/10.0/l10n_it_corrispettivi_sale
Author: Agile Business Group, Odoo Community Association (OCA)
Author-email: support@odoo-community.org
License: AGPL-3
Platform: UNKNOWN
Classifier: Programming Language :: Python
Classifier: Framework :: Odoo
Classifier: License :: OSI Approved :: GNU Affero General Public License v3
Requires-Python: ~=2.7
Requires-Dist: odoo10-addon-l10n-it-corrispettivi
Requires-Dist: odoo (<10.1dev,>=10.0)
